[
    {
      "name": "Bacon McDouble",
      "restaurant": "McDonald's",
      "calories": 460,
      "type": "Burger",
      "vegan": false,
      "glutenFree": false,
      "yearOfRelease": "2010s",
      "game": 1,
      "ingredients": ["bacon", "cheese", "bread", "beef", "pickles", "onions"]
    },
    {
      "name": "Bacon Ranch Deluxe McCrispy",
      "restaurant": "McDonald's",
      "calories": 660,
      "type": "Chicken Sandwich",
      "vegan": false,
      "glutenFree": false,
      "yearOfRelease": "2020s",
      "game": 2,
      "ingredients": ["bacon", "cheese", "ranch dressing", "bread", "chicken", "lettuce", "tomato"]
    },
    {
      "name": "Bacon Ranch McCrispy",
      "restaurant": "McDonald's",
      "calories": 650,
      "type": "Chicken Sandwich",
      "vegan": false,
      "glutenFree": false,
      "yearOfRelease": "2020s",
      "game": 3,
      "ingredients": ["bacon", "cheese", "ranch dressing", "bread", "chicken", "lettuce"]
    },
    {
      "name": "Big Mac",
      "restaurant": "McDonald's",
      "calories": 540,
      "type": "Burger",
      "vegan": false,
      "glutenFree": false,
      "yearOfRelease": "1960s",
      "game": 4,
      "ingredients": ["cheese", "pickles", "lettuce", "onions", "special sauce", "bread", "beef"]
    },
    {
      "name": "Big Mac Bacon",
      "restaurant": "McDonald's",
      "calories": 610,
      "type": "Burger",
      "vegan": false,
      "glutenFree": false,
      "yearOfRelease": "2000s",
      "game": 5,
      "ingredients": ["bacon", "cheese", "pickles", "lettuce", "onions", "special sauce", "bread", "beef"]
    },
    {
      "name": "Cardi B & Offset Meal",
      "restaurant": "McDonald's",
      "calories": 2190,
      "type": "Misc",
      "vegan": false,
      "glutenFree": false,
      "yearOfRelease": "2020s",
      "game": 6,
      "ingredients": ["cheese", "bacon", "chicken", "fries", "soda", "pickles", "bread"]
    },
    {
      "name": "Cheeseburger",
      "restaurant": "McDonald's",
      "calories": 300,
      "type": "Burger",
      "vegan": false,
      "glutenFree": false,
      "yearOfRelease": "1940s",
      "game": 7,
      "ingredients": ["cheese", "pickles", "onions", "bread", "beef"]
    },
    {
      "name": "Cheesy Jalapeno Bacon Quarter Pounder",
      "restaurant": "McDonald's",
      "calories": 650,
      "type": "Burger",
      "vegan": false,
      "glutenFree": false,
      "yearOfRelease": "2010s",
      "game": 8,
      "ingredients": ["cheese", "bacon", "jalapenos", "bread", "beef", "onions"]
    },
    {
      "name": "Chicken Big Mac",
      "restaurant": "McDonald's",
      "calories": 700,
      "type": "Chicken Sandwich",
      "vegan": false,
      "glutenFree": false,
      "yearOfRelease": "2020s",
      "game": 9,
      "ingredients": ["cheese", "pickles", "lettuce", "special sauce", "bread", "chicken"]
    },
    {
      "name": "Daily Double",
      "restaurant": "McDonald's",
      "calories": 440,
      "type": "Burger",
      "vegan": false,
      "glutenFree": false,
      "yearOfRelease": "2000s",
      "game": 10,
      "ingredients": ["cheese", "pickles", "onions", "bread", "beef"]
    },
    {
      "name": "Deluxe McCrispy",
      "restaurant": "McDonald's",
      "calories": 530,
      "type": "Chicken Sandwich",
      "vegan": false,
      "glutenFree": false,
      "yearOfRelease": "2020s",
      "game": 11,
      "ingredients": ["cheese", "bread", "chicken", "lettuce", "tomato"]
    },
    {
      "name": "Double Cheeseburger",
      "restaurant": "McDonald's",
      "calories": 440,
      "type": "Burger",
      "vegan": false,
      "glutenFree": false,
      "yearOfRelease": "2000s",
      "game": 12,
      "ingredients": ["cheese", "pickles", "onions", "bread", "beef"]
    },
    {
      "name": "Double Filet-O-Fish",
      "restaurant": "McDonald's",
      "calories": 540,
      "type": "Fish Sandwich",
      "vegan": false,
      "glutenFree": false,
      "yearOfRelease": "1960s",
      "game": 13,
      "ingredients": ["cheese", "fish fillets", "pickles", "tartar sauce", "bread"]
    },
    {
      "name": "Double Hamburger",
      "restaurant": "McDonald's",
      "calories": 330,
      "type": "Burger",
      "vegan": false,
      "glutenFree": false,
      "yearOfRelease": "2000s",
      "game": 14,
      "ingredients": ["pickles", "onions", "bread", "beef"]
    },
    {
      "name": "Double Quarter Pounder with Cheese",
      "restaurant": "McDonald's",
      "calories": 780,
      "type": "Burger",
      "vegan": false,
      "glutenFree": false,
      "yearOfRelease": "2000s",
      "game": 15,
      "ingredients": ["cheese", "pickles", "onions", "bread", "beef"]
    },
    {
      "name": "Double Quarter Pounder with Cheese Deluxe",
      "restaurant": "McDonald's",
      "calories": 650,
      "type": "Burger",
      "vegan": false,
      "glutenFree": false,
      "yearOfRelease": "2000s",
      "game": 16,
      "ingredients": ["cheese", "pickles", "onions", "lettuce", "tomato", "bread", "beef"]
    },
    {
      "name": "Filet-O-Fish®",
      "restaurant": "McDonald's",
      "calories": 390,
      "type": "Fish Sandwich",
      "vegan": false,
      "glutenFree": false,
      "yearOfRelease": "1960s",
      "game": 17,
      "ingredients": ["cheese", "fish fillets", "pickles", "tartar sauce", "bread"]
    },
    {
      "name": "Hamburger",
      "restaurant": "McDonald's",
      "calories": 250,
      "type": "Burger",
      "vegan": false,
      "glutenFree": false,
      "yearOfRelease": "1940s",
      "game": 18,
      "ingredients": ["pickles", "onions", "bread", "beef"]
    },
    {
      "name": "Hot 'n Spicy McChicken",
      "restaurant": "McDonald's",
      "calories": 380,
      "type": "Chicken Sandwich",
      "vegan": false,
      "glutenFree": false,
      "yearOfRelease": "2000s",
      "game": 19,
      "ingredients": ["bread", "chicken", "spicy mayo", "lettuce"]
    },
    {
      "name": "McChicken",
      "restaurant": "McDonald's",
      "calories": 410,
      "type": "Chicken Sandwich",
      "vegan": false,
      "glutenFree": false,
      "yearOfRelease": "1980s",
      "game": 20,
      "ingredients": ["bread", "chicken", "mayonnaise", "lettuce"]
    },
    {
      "name": "McCrispy Chicken Sandwich",
      "restaurant": "McDonald's",
      "calories": 470,
      "type": "Chicken Sandwich",
      "vegan": false,
      "glutenFree": false,
      "yearOfRelease": "2020s",
      "game": 21,
      "ingredients": ["bread", "chicken", "lettuce", "mayonnaise"]
    },
    {
      "name": "McDouble",
      "restaurant": "McDonald's",
      "calories": 390,
      "type": "Burger",
      "vegan": false,
      "glutenFree": false,
      "yearOfRelease": "2000s",
      "game": 22,
      "ingredients": ["beef", "cheese", "bread", "pickles", "onions", "ketchup", "mustard"]
    },
    {
        "name": "McRib",
        "restaurant": "McDonald's",
        "calories": 520,
        "type": "Misc",
        "vegan": false,
        "glutenFree": false,
        "yearOfRelease": "1980s",
        "game": 23,
        "ingredients": ["pork", "bbq sauce", "bread", "pickles", "onions"]
      },
      {
        "name": "Minecraft Movie Meal",
        "restaurant": "McDonald's",
        "calories": 755,
        "type": "Misc",
        "vegan": false,
        "glutenFree": false,
        "yearOfRelease": "2020s",
        "game": 24,
        "ingredients": ["burger", "fries", "drink"]
      },
      {
        "name": "Quarter Pounder Bacon",
        "restaurant": "McDonald's",
        "calories": 640,
        "type": "Burger",
        "vegan": false,
        "glutenFree": false,
        "yearOfRelease": "2010s",
        "game": 25,
        "ingredients": ["bacon", "cheese", "bread", "beef", "pickles", "onions"]
      },
      {
        "name": "Quarter Pounder Deluxe",
        "restaurant": "McDonald's",
        "calories": 650,
        "type": "Burger",
        "vegan": false,
        "glutenFree": false,
        "yearOfRelease": "2000s",
        "game": 26,
        "ingredients": ["cheese", "bread", "beef", "pickles", "onions", "lettuce", "tomato"]
      },
      {
        "name": "Quarter Pounder® with Cheese",
        "restaurant": "McDonald's",
        "calories": 540,
        "type": "Burger",
        "vegan": false,
        "glutenFree": false,
        "yearOfRelease": "1970s",
        "game": 27,
        "ingredients": ["cheese", "bread", "beef", "pickles", "onions"]
      },
      {
        "name": "Smoky BLT Quarter Pounder with Cheese",
        "restaurant": "McDonald's",
        "calories": 770,
        "type": "Burger",
        "vegan": false,
        "glutenFree": false,
        "yearOfRelease": "2010s",
        "game": 28,
        "ingredients": ["bacon", "cheese", "bread", "beef", "pickles", "onions", "lettuce", "tomato"]
      },
      {
        "name": "Spicy Deluxe McCrispy",
        "restaurant": "McDonald's",
        "calories": 530,
        "type": "Chicken Sandwich",
        "vegan": false,
        "glutenFree": false,
        "yearOfRelease": "2020s",
        "game": 29,
        "ingredients": ["spicy chicken", "cheese", "bread", "pickles", "lettuce", "mayo"]
      },
      {
        "name": "Spicy McCrispy",
        "restaurant": "McDonald's",
        "calories": 530,
        "type": "Chicken Sandwich",
        "vegan": false,
        "glutenFree": false,
        "yearOfRelease": "2020s",
        "game": 30,
        "ingredients": ["spicy chicken", "bread", "pickles", "lettuce", "mayo"]
      },
      {
        "name": "Triple Cheeseburger",
        "restaurant": "McDonald's",
        "calories": 0,
        "type": "Burger",
        "vegan": false,
        "glutenFree": false,
        "yearOfRelease": "2010s",
        "game": 31,
        "ingredients": ["cheese", "bread", "beef", "pickles", "onions"]
      },
      {
        "name": "Apple Fritter",
        "restaurant": "McDonald's",
        "calories": 510,
        "type": "Dessert",
        "vegan": false,
        "glutenFree": false,
        "yearOfRelease": "2000s",
        "game": 32,
        "ingredients": ["apple", "flour", "sugar", "cinnamon"]
      },
      {
        "name": "Bacon, Egg & Cheese Bagel",
        "restaurant": "McDonald's",
        "calories": 550,
        "type": "Breakfast",
        "vegan": false,
        "glutenFree": false,
        "yearOfRelease": "2000s",
        "game": 33,
        "ingredients": ["bacon", "egg", "cheese", "bagel"]
      },
      {
        "name": "Bacon, Egg & Cheese Biscuit",
        "restaurant": "McDonald's",
        "calories": 450,
        "type": "Breakfast",
        "vegan": false,
        "glutenFree": false,
        "yearOfRelease": "2000s",
        "game": 34,
        "ingredients": ["bacon", "egg", "cheese", "biscuit"]
      },
      {
        "name": "Bacon, Egg & Cheese McGriddles",
        "restaurant": "McDonald's",
        "calories": 420,
        "type": "Breakfast",
        "vegan": false,
        "glutenFree": false,
        "yearOfRelease": "2000s",
        "game": 35,
        "ingredients": ["bacon", "egg", "cheese", "griddles"]
      },
      {
        "name": "Big Breakfast with Hotcakes",
        "restaurant": "McDonald's",
        "calories": 1340,
        "type": "Breakfast",
        "vegan": false,
        "glutenFree": false,
        "yearOfRelease": "1970s",
        "game": 36,
        "ingredients": ["egg", "sausage", "hash browns", "hotcakes", "syrup"]
      },
      {
        "name": "Big Breakfast®",
        "restaurant": "McDonald's",
        "calories": 750,
        "type": "Breakfast",
        "vegan": false,
        "glutenFree": false,
        "yearOfRelease": "1970s",
        "game": 37,
        "ingredients": ["egg", "sausage", "hash browns"]
      },
      {
        "name": "Blueberry Muffin",
        "restaurant": "McDonald's",
        "calories": 470,
        "type": "Dessert",
        "vegan": false,
        "glutenFree": false,
        "yearOfRelease": "2000s",
        "game": 38,
        "ingredients": ["blueberries", "flour", "sugar", "butter"]
      },
      {
        "name": "Cinnamon Roll",
        "restaurant": "McDonald's",
        "calories": 560,
        "type": "Dessert",
        "vegan": false,
        "glutenFree": false,
        "yearOfRelease": "2000s",
        "game": 39,
        "ingredients": ["cinnamon", "flour", "sugar", "butter"]
      },
      {
        "name": "Egg McMuffin",
        "restaurant": "McDonald's",
        "calories": 300,
        "type": "Breakfast",
        "vegan": false,
        "glutenFree": false,
        "yearOfRelease": "1970s",
        "game": 40,
        "ingredients": ["egg", "cheese", "ham", "english muffin"]
      },
      {
        "name": "Fruit & Maple Oatmeal",
        "restaurant": "McDonald's",
        "calories": 260,
        "type": "Breakfast",
        "vegan": true,
        "glutenFree": false,
        "yearOfRelease": "2000s",
        "game": 41,
        "ingredients": ["oats", "fruit", "maple syrup"]
      },
      {
        "name": "Hash Brown",
        "restaurant": "McDonald's",
        "calories": 150,
        "type": "Side",
        "vegan": false,
        "glutenFree": false,
        "yearOfRelease": "1970s",
        "game": 42,
        "ingredients": ["potatoes", "oil", "salt"]
      },
      {
        "name": "Hotcakes",
        "restaurant": "McDonald's",
        "calories": 590,
        "type": "Breakfast",
        "vegan": false,
        "glutenFree": false,
        "yearOfRelease": "1970s",
        "game": 43,
        "ingredients": ["flour", "eggs", "butter", "syrup"]
      },
      {
        "name": "Hotcakes and Sausage",
        "restaurant": "McDonald's",
        "calories": 780,
        "type": "Breakfast",
        "vegan": false,
        "glutenFree": false,
        "yearOfRelease": "1970s",
        "game": 44,
        "ingredients": ["flour", "eggs", "butter", "syrup", "sausage"]
      },
      {
        "name": "Sausage Biscuit",
        "restaurant": "McDonald's",
        "calories": 460,
        "type": "Breakfast",
        "vegan": false,
        "glutenFree": false,
        "yearOfRelease": "2000s",
        "game": 45,
        "ingredients": ["sausage", "biscuit"]
    },
    {
      "name": "Sausage Biscuit with Egg",
      "restaurant": "McDonald's",
      "calories": 530,
      "type": "Breakfast",
      "vegan": false,
      "glutenFree": false,
      "yearOfRelease": "2000s",
      "game": 46,
      "ingredients": ["sausage", "egg", "biscuit"]
    },
    {
      "name": "Sausage Burrito",
      "restaurant": "McDonald's",
      "calories": 300,
      "type": "Breakfast",
      "vegan": false,
      "glutenFree": false,
      "yearOfRelease": "2000s",
      "game": 47,
      "ingredients": ["sausage", "egg", "cheese", "tortilla"]
    },
    {
      "name": "Sausage McGriddles®",
      "restaurant": "McDonald's",
      "calories": 430,
      "type": "Breakfast",
      "vegan": false,
      "glutenFree": false,
      "yearOfRelease": "2000s",
      "game": 48,
      "ingredients": ["sausage", "egg", "cheese", "griddles"]
    },
    {
      "name": "Sausage McMuffin®",
      "restaurant": "McDonald's",
      "calories": 400,
      "type": "Breakfast",
      "vegan": false,
      "glutenFree": false,
      "yearOfRelease": "1970s",
      "game": 49,
      "ingredients": ["sausage", "egg", "cheese", "english muffin"]
    },
    {
      "name": "Sausage McMuffin® with Egg",
      "restaurant": "McDonald's",
      "calories": 480,
      "type": "Breakfast",
      "vegan": false,
      "glutenFree": false,
      "yearOfRelease": "1970s",
      "game": 50,
      "ingredients": ["sausage", "egg", "cheese", "english muffin"]
    },
    {
      "name": "Sausage, Egg & Cheese McGriddles",
      "restaurant": "McDonald's",
      "calories": 550,
      "type": "Breakfast",
      "vegan": false,
      "glutenFree": false,
      "yearOfRelease": "2000s",
      "game": 51,
      "ingredients": ["sausage", "egg", "cheese", "griddles"]
    },
    {
      "name": "Apple Slices",
      "restaurant": "McDonald's",
      "calories": 15,
      "type": "Side",
      "vegan": true,
      "glutenFree": true,
      "yearOfRelease": "2000s",
      "game": 52,
      "ingredients": ["apple"]
    },
    {
      "name": "French Fries, Large",
      "restaurant": "McDonald's",
      "calories": 522,
      "type": "Side",
      "vegan": false,
      "glutenFree": false,
      "yearOfRelease": "1940s",
      "game": 53,
      "ingredients": ["potatoes", "oil", "salt"]
    },
    {
      "name": "Side Salad",
      "restaurant": "McDonald's",
      "calories": 15,
      "type": "Side",
      "vegan": true,
      "glutenFree": true,
      "yearOfRelease": "2000s",
      "game": 54,
      "ingredients": ["lettuce", "tomato", "cucumbers", "dressing"]
    },
    {
      "name": "Strawberry Gogurt",
      "restaurant": "McDonald's",
      "calories": 45,
      "type": "Dessert",
      "vegan": false,
      "glutenFree": false,
      "yearOfRelease": "2000s",
      "game": 55,
      "ingredients": ["strawberries", "yogurt", "sugar"]
    },
    {
      "name": "Chicken McNuggets, 6 piece",
      "restaurant": "McDonald's",
      "calories": 270,
      "type": "Side",
      "vegan": false,
      "glutenFree": false,
      "yearOfRelease": "1980s",
      "game": 56,
      "ingredients": ["chicken", "breading", "oil"]
    },
      {
        "name": "Bean Burrito",
        "restaurant": "Taco Bell",
        "calories": 350,
        "type": "Burrito",
        "vegan": false,
        "glutenFree": false,
        "yearOfRelease": "1990s",
        "game": 57,
        "ingredients": ["beans", "cheese", "sour cream", "onions", "tortilla"]
      },
      {
        "name": "Beefy 5-Layer Burrito",
        "restaurant": "Taco Bell",
        "calories": 490,
        "type": "Burrito",
        "vegan": false,
        "glutenFree": false,
        "yearOfRelease": "2000s",
        "game": 58,
        "ingredients": ["beef", "cheese", "sour cream", "taco sauce", "tortilla", "beans"]
      },
      {
        "name": "Burrito Supreme - Chicken",
        "restaurant": "Taco Bell",
        "calories": 370,
        "type": "Burrito",
        "vegan": false,
        "glutenFree": false,
        "yearOfRelease": "2000s",
        "game": 59,
        "ingredients": ["chicken", "cheese", "lettuce", "tomato", "sour cream", "taco sauce", "tortilla"]
      },
      {
        "name": "Burrito Supreme - Steak",
        "restaurant": "Taco Bell",
        "calories": 370,
        "type": "Burrito",
        "vegan": false,
        "glutenFree": false,
        "yearOfRelease": "2000s",
        "game": 60,
        "ingredients": ["steak", "cheese", "lettuce", "tomato", "sour cream", "taco sauce", "tortilla"]
      },
      {
        "name": "Burrito Supreme – Beef",
        "restaurant": "Taco Bell",
        "calories": 390,
        "type": "Burrito",
        "vegan": false,
        "glutenFree": false,
        "yearOfRelease": "2000s",
        "game": 61,
        "ingredients": ["beef", "cheese", "lettuce", "tomato", "sour cream", "taco sauce", "tortilla"]
      },
      {
        "name": "Cheesy Bean and Rice Burrito",
        "restaurant": "Taco Bell",
        "calories": 410,
        "type": "Burrito",
        "vegan": false,
        "glutenFree": false,
        "yearOfRelease": "2000s",
        "game": 62,
        "ingredients": ["beans", "rice", "cheese", "taco sauce", "tortilla"]
      },
      {
        "name": "Chicken Enchilada Burrito",
        "restaurant": "Taco Bell",
        "calories": 380,
        "type": "Burrito",
        "vegan": false,
        "glutenFree": false,
        "yearOfRelease": "2000s",
        "game": 63,
        "ingredients": ["chicken", "cheese", "enchilada sauce", "onions", "tortilla"]
      },
      {
        "name": "Green Burrito",
        "restaurant": "Taco Bell",
        "calories": 370,
        "type": "Burrito",
        "vegan": false,
        "glutenFree": false,
        "yearOfRelease": "2020s",
        "game": 64,
        "ingredients": ["beef", "cheese", "guacamole", "lettuce", "sour cream", "tortilla"]
      },
      {
        "name": "Grilled Cheese Burrito",
        "restaurant": "Taco Bell",
        "calories": 710,
        "type": "Burrito",
        "vegan": false,
        "glutenFree": false,
        "yearOfRelease": "2020s",
        "game": 65,
        "ingredients": ["beef", "cheese", "nacho cheese", "sour cream", "taco sauce", "tortilla"]
      },
      {
        "name": "Veggie Burrito Supreme",
        "restaurant": "Taco Bell",
        "calories": 390,
        "type": "Burrito",
        "vegan": true,
        "glutenFree": false,
        "yearOfRelease": "2000s",
        "game": 66,
        "ingredients": ["beans", "cheese", "lettuce", "tomato", "sour cream", "taco sauce", "tortilla"]
      },
        {
            "name": "Black Bean Soft Taco",
            "restaurant": "Taco Bell",
            "calories": 170,
            "type": "Taco",
            "vegan": true,
            "glutenFree": false,
            "yearOfRelease": "2000s",
            "game": 67,
            "ingredients": ["black beans", "cheese", "lettuce", "taco sauce", "soft tortilla"]
          },
          {
            "name": "Crunchy Taco",
            "restaurant": "Taco Bell",
            "calories": 170,
            "type": "Taco",
            "vegan": false,
            "glutenFree": false,
            "yearOfRelease": "1960s",
            "game": 68,
            "ingredients": ["beef", "cheese", "lettuce", "taco sauce", "taco shell"]
          },
          {
            "name": "Crunchy Taco Supreme",
            "restaurant": "Taco Bell",
            "calories": 190,
            "type": "Taco",
            "vegan": false,
            "glutenFree": false,
            "yearOfRelease": "1990s",
            "game": 69,
            "ingredients": ["beef", "cheese", "lettuce", "tomato", "sour cream", "taco sauce", "taco shell"]
          },
          {
            "name": "Nacho Cheese Doritos Locos Taco",
            "restaurant": "Taco Bell",
            "calories": 170,
            "type": "Taco",
            "vegan": false,
            "glutenFree": false,
            "yearOfRelease": "2010s",
            "game": 70,
            "ingredients": ["beef", "cheese", "lettuce", "taco sauce", "doritos taco shell"]
          },
          {
            "name": "Nacho Cheese Doritos Locos Taco Supreme",
            "restaurant": "Taco Bell",
            "calories": 190,
            "type": "Taco",
            "vegan": false,
            "glutenFree": false,
            "yearOfRelease": "2010s",
            "game": 71,
            "ingredients": ["beef", "cheese", "lettuce", "tomato", "sour cream", "taco sauce", "doritos taco shell"]
          },
          {
            "name": "Soft Taco - Beef",
            "restaurant": "Taco Bell",
            "calories": 180,
            "type": "Taco",
            "vegan": false,
            "glutenFree": false,
            "yearOfRelease": "1980s",
            "game": 72,
            "ingredients": ["beef", "cheese", "lettuce", "taco sauce", "tortilla"]
          },
          {
            "name": "Soft Taco Supreme – Beef",
            "restaurant": "Taco Bell",
            "calories": 210,
            "type": "Taco",
            "vegan": false,
            "glutenFree": false,
            "yearOfRelease": "1990s",
            "game": 73,
            "ingredients": ["beef", "cheese", "lettuce", "tomato", "sour cream", "taco sauce", "tortilla"]
          },
          {
            "name": "Spicy Potato Soft Taco",
            "restaurant": "Taco Bell",
            "calories": 230,
            "type": "Taco",
            "vegan": true,
            "glutenFree": false,
            "yearOfRelease": "2010s",
            "game": 74,
            "ingredients": ["potatoes", "cheese", "lettuce", "sour cream", "taco sauce", "tortilla"]
          },
          {
            "name": "Breakfast California Crunchwrap",
            "restaurant": "Taco Bell",
            "calories": 630,
            "type": "Breakfast",
            "vegan": false,
            "glutenFree": false,
            "yearOfRelease": "2010s",
            "game": 75,
            "ingredients": ["eggs", "bacon", "cheese", "hash brown", "tomato", "sour cream", "tortilla"]
          },
          {
            "name": "Breakfast Crunchwrap - Bacon",
            "restaurant": "Taco Bell",
            "calories": 670,
            "type": "Breakfast",
            "vegan": false,
            "glutenFree": false,
            "yearOfRelease": "2010s",
            "game": 76,
            "ingredients": ["eggs", "bacon", "cheese", "hash brown", "sour cream", "tortilla"]
          },
          {
            "name": "Breakfast Crunchwrap - Sausage",
            "restaurant": "Taco Bell",
            "calories": 710,
            "type": "Breakfast",
            "vegan": false,
            "glutenFree": false,
            "yearOfRelease": "2010s",
            "game": 77,
            "ingredients": ["eggs", "sausage", "cheese", "hash brown", "sour cream", "tortilla"]
          },
          {
            "name": "Breakfast Crunchwrap - Steak",
            "restaurant": "Taco Bell",
            "calories": 660,
            "type": "Breakfast",
            "vegan": false,
            "glutenFree": false,
            "yearOfRelease": "2010s",
            "game": 78,
            "ingredients": ["eggs", "steak", "cheese", "hash brown", "sour cream", "tortilla"]
          },
          {
            "name": "Breakfast Quesadilla",
            "restaurant": "Taco Bell",
            "calories": 510,
            "type": "Breakfast",
            "vegan": false,
            "glutenFree": false,
            "yearOfRelease": "2000s",
            "game": 79,
            "ingredients": ["eggs", "cheese", "bacon", "tortilla"]
          },
          {
            "name": "Cheesy Toasted Breakfast Burrito",
            "restaurant": "Taco Bell",
            "calories": 340,
            "type": "Breakfast",
            "vegan": false,
            "glutenFree": false,
            "yearOfRelease": "2000s",
            "game": 80,
            "ingredients": ["eggs", "cheese", "bacon", "tortilla"]
          },
          {
            "name": "Cinnabon Delights",
            "restaurant": "Taco Bell",
            "calories": 160,
            "type": "Dessert",
            "vegan": false,
            "glutenFree": false,
            "yearOfRelease": "2000s",
            "game": 81,
            "ingredients": ["cinnamon", "cream cheese", "dough"]
          },
          {
            "name": "Grande Toasted Breakfast Burrito",
            "restaurant": "Taco Bell",
            "calories": 560,
            "type": "Breakfast",
            "vegan": false,
            "glutenFree": false,
            "yearOfRelease": "2000s",
            "game": 82,
            "ingredients": ["eggs", "cheese", "bacon", "hash brown", "tortilla"]
          },
          {
            "name": "Hash Brown",
            "restaurant": "Taco Bell",
            "calories": 160,
            "type": "Side",
            "vegan": true,
            "glutenFree": true,
            "yearOfRelease": "1980s",
            "game": 83,
            "ingredients": ["potato", "oil", "salt"]
          },
          {
            "name": "Caliente Cantina Chicken Bowl",
            "restaurant": "Taco Bell",
            "calories": 480,
            "type": "Bowl",
            "vegan": false,
            "glutenFree": false,
            "yearOfRelease": "2020s",
            "game": 84,
            "ingredients": ["chicken", "rice", "cheese", "sour cream", "guacamole", "lettuce", "tortilla strips"]
          },
          {
            "name": "Caliente Cantina Chicken Burrito",
            "restaurant": "Taco Bell",
            "calories": 450,
            "type": "Burrito",
            "vegan": false,
            "glutenFree": false,
            "yearOfRelease": "2020s",
            "game": 85,
            "ingredients": ["chicken", "rice", "cheese", "sour cream", "guacamole", "tortilla"]
          },
          {
            "name": "Caliente Cantina Chicken Crispy Taco",
            "restaurant": "Taco Bell",
            "calories": 290,
            "type": "Taco",
            "vegan": false,
            "glutenFree": false,
            "yearOfRelease": "2020s",
            "game": 86,
            "ingredients": ["crispy chicken", "cheese", "lettuce", "taco shell"]
          },
          {
            "name": "Caliente Cantina Chicken Quesadilla",
            "restaurant": "Taco Bell",
            "calories": 560,
            "type": "Quesadilla",
            "vegan": false,
            "glutenFree": false,
            "yearOfRelease": "2020s",
            "game": 87,
            "ingredients": ["chicken", "cheese", "flour tortilla", "sour cream"]
          },
          {
            "name": "Caliente Cantina Chicken Soft Taco",
            "restaurant": "Taco Bell",
            "calories": 200,
            "type": "Taco",
            "vegan": false,
            "glutenFree": false,
            "yearOfRelease": "2020s",
            "game": 88,
            "ingredients": ["chicken", "cheese", "lettuce", "soft taco shell"]
          },
          {
            "name": "Cantina Chicken Bowl",
            "restaurant": "Taco Bell",
            "calories": 490,
            "type": "Bowl",
            "vegan": false,
            "glutenFree": false,
            "yearOfRelease": "2020s",
            "game": 89,
            "ingredients": ["chicken", "rice", "cheese", "sour cream", "guacamole", "lettuce", "tortilla strips"]
          },
          {
            "name": "Cantina Chicken Burrito",
            "restaurant": "Taco Bell",
            "calories": 540,
            "type": "Burrito",
            "vegan": false,
            "glutenFree": false,
            "yearOfRelease": "2020s",
            "game": 90,
            "ingredients": ["chicken", "rice", "cheese", "sour cream", "guacamole", "tortilla"]
          },
          {
            "name": "Cantina Chicken Quesadilla",
            "restaurant": "Taco Bell",
            "calories": 570,
            "type": "Quesadilla",
            "vegan": false,
            "glutenFree": false,
            "yearOfRelease": "2020s",
            "game": 91,
            "ingredients": ["chicken", "cheese", "flour tortilla", "sour cream"]
          },
          {
            "name": "Cantina Chicken Soft Taco",
            "restaurant": "Taco Bell",
            "calories": 210,
            "type": "Taco",
            "vegan": false,
            "glutenFree": false,
            "yearOfRelease": "2020s",
            "game": 92,
            "ingredients": ["chicken", "cheese", "lettuce", "soft taco shell"]
          },
          {
            "name": "Cantina Crispy Chicken Taco",
            "restaurant": "Taco Bell",
            "calories": 270,
            "type": "Taco",
            "vegan": false,
            "glutenFree": false,
            "yearOfRelease": "2020s",
            "game": 93,
            "ingredients": ["crispy chicken", "cheese", "lettuce", "taco shell"]
          },
          {
            "name": "Black Bean Chalupa",
            "restaurant": "Taco Bell",
            "calories": 330,
            "type": "Chalupa",
            "vegan": true,
            "glutenFree": false,
            "yearOfRelease": "2000s",
            "game": 94,
            "ingredients": ["black beans", "cheese", "lettuce", "tomato", "chalupa shell", "sour cream"]
          },
          {
            "name": "Chalupa Supreme - Chicken",
            "restaurant": "Taco Bell",
            "calories": 330,
            "type": "Chalupa",
            "vegan": false,
            "glutenFree": false,
            "yearOfRelease": "2000s",
            "game": 95,
            "ingredients": ["chicken", "cheese", "lettuce", "tomato", "chalupa shell", "sour cream"]
          },
          {
            "name": "Chalupa Supreme - Steak",
            "restaurant": "Taco Bell",
            "calories": 330,
            "type": "Chalupa",
            "vegan": false,
            "glutenFree": false,
            "yearOfRelease": "2000s",
            "game": 96,
            "ingredients": ["steak", "cheese", "lettuce", "tomato", "chalupa shell", "sour cream"]
          },
          {
            "name": "Chalupa Supreme – Beef",
            "restaurant": "Taco Bell",
            "calories": 350,
            "type": "Chalupa",
            "vegan": false,
            "glutenFree": false,
            "yearOfRelease": "2000s",
            "game": 97,
            "ingredients": ["beef", "cheese", "lettuce", "tomato", "chalupa shell", "sour cream"]
          },
          {
            "name": "Chipotle Chicken and Cheese, 6 Inch",
            "restaurant": "Subway",
            "calories": 450,
            "type": "Sandwich",
            "vegan": false,
            "glutenFree": false,
            "yearOfRelease": "2000s",
            "game": 98,
            "ingredients": ["chicken", "cheese", "chipotle sauce", "lettuce", "tomato", "onions", "sandwich bread"]
          },
          {
            "name": "All American Club, 6 Inch",
            "restaurant": "Subway",
            "calories": 450,
            "type": "Sandwich",
            "vegan": false,
            "glutenFree": false,
            "yearOfRelease": "2000s",
            "game": 99,
            "ingredients": ["turkey", "ham", "cheese", "lettuce", "tomato", "mayonnaise", "sandwich bread"]
          },
          {
            "name": "All-Pro Sweet Onion Teriyaki, 6 Inch",
            "restaurant": "Subway",
            "calories": 430,
            "type": "Sandwich",
            "vegan": false,
            "glutenFree": false,
            "yearOfRelease": "2000s",
            "game": 100,
            "ingredients": ["chicken", "sweet onion sauce", "lettuce", "tomato", "sandwich bread"]
          },
          {
            "name": "B.L.T., 6 Inch",
            "restaurant": "Subway",
            "calories": 330,
            "type": "Sandwich",
            "vegan": false,
            "glutenFree": false,
            "yearOfRelease": "1960s",
            "game": 101,
            "ingredients": ["bacon", "lettuce", "tomato", "mayonnaise", "sandwich bread"]
          },
          {
            "name": "Bella Mozza, 6 Inch",
            "restaurant": "Subway",
            "calories": 420,
            "type": "Sandwich",
            "vegan": false,
            "glutenFree": false,
            "yearOfRelease": "2010s",
            "game": 102,
            "ingredients": ["mozzarella cheese", "tomato", "basil", "olive oil", "sandwich bread"]
          },
          {
            "name": "Benissimo Sandwich, 6 Inch",
            "restaurant": "Subway",
            "calories": 510,
            "type": "Sandwich",
            "vegan": false,
            "glutenFree": false,
            "yearOfRelease": "2000s",
            "game": 103,
            "ingredients": ["ham", "salami", "cheese", "lettuce", "tomato", "sandwich bread"]
          },
          {
            "name": "Big Hot Pastrami, 6 Inch",
            "restaurant": "Subway",
            "calories": 470,
            "type": "Sandwich",
            "vegan": false,
            "glutenFree": false,
            "yearOfRelease": "2000s",
            "game": 104,
            "ingredients": ["pastrami", "cheese", "mustard", "lettuce", "tomato", "sandwich bread"]
          },
          {
            "name": "Black Forest Ham, 6 Inch",
            "restaurant": "Subway",
            "calories": 270,
            "type": "Sandwich",
            "vegan": false,
            "glutenFree": false,
            "yearOfRelease": "1980s",
            "game": 105,
            "ingredients": ["ham", "lettuce", "tomato", "mayonnaise", "sandwich bread"]
          },
          {
            "name": "Buffalo Chicken Sandwich, 6 Inch",
            "restaurant": "Subway",
            "calories": 340,
            "type": "Sandwich",
            "vegan": false,
            "glutenFree": false,
            "yearOfRelease": "2000s",
            "game": 106,
            "ingredients": ["chicken", "buffalo sauce", "lettuce", "tomato", "sandwich bread"]
          },
          {
            "name": "Chicken & Bacon Ranch, 6 Inch",
            "restaurant": "Subway",
            "calories": 530,
            "type": "Sandwich",
            "vegan": false,
            "glutenFree": false,
            "yearOfRelease": "2000s",
            "game": 107,
            "ingredients": ["chicken", "bacon", "ranch sauce", "cheese", "lettuce", "tomato", "sandwich bread"]
          },
          {
            "name": "Cold Cut Combo, 6 Inch",
            "restaurant": "Subway",
            "calories": 280,
            "type": "Sandwich",
            "vegan": false,
            "glutenFree": false,
            "yearOfRelease": "1970s",
            "game": 108,
            "ingredients": ["ham", "salami", "bologna", "lettuce", "tomato", "mayonnaise", "sandwich bread"]
          },
          {
            "name": "Elite Chicken & Bacon Ranch, 6 Inch",
            "restaurant": "Subway",
            "calories": 570,
            "type": "Sandwich",
            "vegan": false,
            "glutenFree": false,
            "yearOfRelease": "2000s",
            "game": 109,
            "ingredients": ["chicken", "bacon", "ranch sauce", "cheese", "lettuce", "tomato", "sandwich bread"]
          },
          {
            "name": "Garlic Roast Beef, 6 Inch",
            "restaurant": "Subway",
            "calories": 480,
            "type": "Sandwich",
            "vegan": false,
            "glutenFree": false,
            "yearOfRelease": "2000s",
            "game": 110,
            "ingredients": ["roast beef", "garlic sauce", "cheese", "lettuce", "tomato", "sandwich bread"]
          },
          {
            "name": "Grand Slam Ham, 6 Inch",
            "restaurant": "Subway",
            "calories": 500,
            "type": "Sandwich",
            "vegan": false,
            "glutenFree": false,
            "yearOfRelease": "2000s",
            "game": 111,
            "ingredients": ["ham", "cheese", "lettuce", "tomato", "sandwich bread"]
          },
          {
            "name": "Ham & Jack Slider, 6 Inch",
            "restaurant": "Subway",
            "calories": 150,
            "type": "Sandwich",
            "vegan": false,
            "glutenFree": false,
            "yearOfRelease": "2010s",
            "game": 112,
            "ingredients": ["ham", "cheese", "sandwich bread"]
          },
          {
            "name": "Hotshot Italiano, 6 Inch",
            "restaurant": "Subway",
            "calories": 620,
            "type": "Sandwich",
            "vegan": false,
            "glutenFree": false,
            "yearOfRelease": "2000s",
            "game": 113,
            "ingredients": ["italian sausage", "pepperoni", "cheese", "lettuce", "tomato", "sandwich bread"]
          },
          {
            "name": "Italian B.M.T., 6 Inch",
            "restaurant": "Subway",
            "calories": 360,
            "type": "Sandwich",
            "vegan": false,
            "glutenFree": false,
            "yearOfRelease": "1970s",
            "game": 114,
            "ingredients": ["salami", "pepperoni", "ham", "cheese", "lettuce", "tomato", "sandwich bread"]
          },
          {
            "name": "Italian Spice Slider, 6 Inch",
            "restaurant": "Subway",
            "calories": 230,
            "type": "Sandwich",
            "vegan": false,
            "glutenFree": false,
            "yearOfRelease": "2010s",
            "game": 115,
            "ingredients": ["italian sausage", "cheese", "sandwich bread"]
          },
          {
            "name": "Little Cheesesteak Slider, 6 Inch",
            "restaurant": "Subway",
            "calories": 180,
            "type": "Sandwich",
            "vegan": false,
            "glutenFree": false,
            "yearOfRelease": "2010s",
            "game": 116,
            "ingredients": ["beef", "cheese", "sandwich bread"]
          },
          {
            "name": "Little Turkey Slider, 6 Inch",
            "restaurant": "Subway",
            "calories": 200,
            "type": "Sandwich",
            "vegan": false,
            "glutenFree": false,
            "yearOfRelease": "2010s",
            "game": 117,
            "ingredients": ["turkey", "cheese", "sandwich bread"]
          },
          {
            "name": "Meatball Marinara, 6 Inch",
            "restaurant": "Subway",
            "calories": 410,
            "type": "Sandwich",
            "vegan": false,
            "glutenFree": false,
            "yearOfRelease": "1970s",
            "game": 118,
            "ingredients": ["meatballs", "marinara sauce", "cheese", "sandwich bread"]
          },
          {
            "name": "Oven Roasted Chicken, 6 Inch",
            "restaurant": "Subway",
            "calories": 280,
            "type": "Sandwich",
            "vegan": false,
            "glutenFree": false,
            "yearOfRelease": "2000s",
            "game": 119,
            "ingredients": ["chicken", "lettuce", "tomato", "mayonnaise", "sandwich bread"]
          },
          {
            "name": "Oven Roasted Turkey, 6 Inch",
            "restaurant": "Subway",
            "calories": 260,
            "type": "Sandwich",
            "vegan": false,
            "glutenFree": false,
            "yearOfRelease": "1980s",
            "game": 120,
            "ingredients": ["turkey", "lettuce", "tomato", "mayonnaise", "sandwich bread"]
          },
          {
            "name": "Oven Roasted Turkey & Ham, 6 Inch",
            "restaurant": "Subway",
            "calories": 270,
            "type": "Sandwich",
            "vegan": false,
            "glutenFree": false,
            "yearOfRelease": "1980s",
            "game": 121,
            "ingredients": ["turkey", "ham", "lettuce", "tomato", "mayonnaise", "sandwich bread"]
          },
          {
            "name": "Roast Beef, 6 Inch",
            "restaurant": "Subway",
            "calories": 200,
            "type": "Sandwich",
            "vegan": false,
            "glutenFree": false,
            "yearOfRelease": "1970s",
            "game": 122,
            "ingredients": ["roast beef", "lettuce", "tomato", "mayonnaise", "sandwich bread"]
          },
          {
            "name": "Rotisserie Style Chicken, 6 Inch",
            "restaurant": "Subway",
            "calories": 300,
            "type": "Sandwich",
            "vegan": false,
            "glutenFree": false,
            "yearOfRelease": "2010s",
            "game": 123,
            "ingredients": ["rotisserie chicken", "lettuce", "tomato", "mayonnaise", "sandwich bread"]
          },
          {
            "name": "Spicy Italian, 6 Inch",
            "restaurant": "Subway",
            "calories": 430,
            "type": "Sandwich",
            "vegan": false,
            "glutenFree": false,
            "yearOfRelease": "1990s",
            "game": 124,
            "ingredients": ["pepperoni", "salami", "lettuce", "tomato", "sandwich bread"]
          },
          {
            "name": "Steak and Cheese, 6 Inch",
            "restaurant": "Subway",
            "calories": 320,
            "type": "Sandwich",
            "vegan": false,
            "glutenFree": false,
            "yearOfRelease": "2000s",
            "game": 125,
            "ingredients": ["steak", "cheese", "lettuce", "tomato", "mayonnaise", "sandwich bread"]
          },
          {
            "name": "Subway Club, 6 Inch",
            "restaurant": "Subway",
            "calories": 460,
            "type": "Sandwich",
            "vegan": false,
            "glutenFree": false,
            "yearOfRelease": "1980s",
            "game": 126,
            "ingredients": ["turkey", "ham", "roast beef", "lettuce", "tomato", "mayonnaise", "sandwich bread"]
          },
          {
            "name": "Supreme Meats Sandwich, 6 Inch",
            "restaurant": "Subway",
            "calories": 510,
            "type": "Sandwich",
            "vegan": false,
            "glutenFree": false,
            "yearOfRelease": "2000s",
            "game": 127,
            "ingredients": ["salami", "pepperoni", "ham", "roast beef", "lettuce", "tomato", "sandwich bread"]
          },
          {
            "name": "Sweet Onion Chicken Teriyaki, 6 Inch",
            "restaurant": "Subway",
            "calories": 340,
            "type": "Sandwich",
            "vegan": false,
            "glutenFree": false,
            "yearOfRelease": "2000s",
            "game": 128,
            "ingredients": ["chicken teriyaki", "lettuce", "tomato", "sweet onion sauce", "sandwich bread"]
          },
          {
            "name": "Teriyaki Blitz, 6 Inch",
            "restaurant": "Subway",
            "calories": 450,
            "type": "Sandwich",
            "vegan": false,
            "glutenFree": false,
            "yearOfRelease": "2010s",
            "game": 129,
            "ingredients": ["chicken teriyaki", "cheese", "lettuce", "tomato", "sandwich bread"]
          },
          {
            "name": "The Beast, 6 Inch",
            "restaurant": "Subway",
            "calories": 730,
            "type": "Sandwich",
            "vegan": false,
            "glutenFree": false,
            "yearOfRelease": "2010s",
            "game": 130,
            "ingredients": ["beef", "steak", "pepperoni", "cheese", "lettuce", "tomato", "sandwich bread"]
          },
          {
            "name": "The Boss, 6 Inch",
            "restaurant": "Subway",
            "calories": 580,
            "type": "Sandwich",
            "vegan": false,
            "glutenFree": false,
            "yearOfRelease": "2010s",
            "game": 131,
            "ingredients": ["bacon", "steak", "cheese", "lettuce", "tomato", "mayonnaise", "sandwich bread"]
          },
          {
            "name": "The Champ, 6 Inch",
            "restaurant": "Subway",
            "calories": 440,
            "type": "Sandwich",
            "vegan": false,
            "glutenFree": false,
            "yearOfRelease": "2010s",
            "game": 132,
            "ingredients": ["ham", "turkey", "cheese", "lettuce", "tomato", "sandwich bread"]
          },
          {
            "name": "The Great Garlic, 6 Inch",
            "restaurant": "Subway",
            "calories": 470,
            "type": "Sandwich",
            "vegan": false,
            "glutenFree": false,
            "yearOfRelease": "2010s",
            "game": 133,
            "ingredients": ["roast beef", "cheese", "garlic aioli", "lettuce", "tomato", "sandwich bread"]
          },
          {
            "name": "Bacon & Cheese Whopper",
            "restaurant": "Burger King",
            "calories": 790,
            "type": "Burger",
            "vegan": false,
            "glutenFree": false,
            "yearOfRelease": "2000s",
            "game": 134,
            "ingredients": ["bacon", "cheese", "lettuce", "tomato", "onions", "pickles", "ketchup", "mayonnaise", "burger bun", "beef"]
          },
          {
            "name": "Bacon Cheeseburger",
            "restaurant": "Burger King",
            "calories": 317,
            "type": "Burger",
            "vegan": false,
            "glutenFree": false,
            "yearOfRelease": "2000s",
            "game": 135,
            "ingredients": ["bacon", "cheese", "ketchup", "mustard", "pickles", "onions", "burger bun", "beef"]
          },
          {
            "name": "Bacon Double Cheeseburger",
            "restaurant": "Burger King",
            "calories": 405,
            "type": "Burger",
            "vegan": false,
            "glutenFree": false,
            "yearOfRelease": "2000s",
            "game": 136,
            "ingredients": ["bacon", "cheese", "ketchup", "mustard", "pickles", "onions", "burger bun", "beef"]
          },
          {
            "name": "Bacon King",
            "restaurant": "Burger King",
            "calories": "1250",
            "type": "Burger",
            "vegan": false,
            "glutenFree": false,
            "yearOfRelease": "2010s",
            "game": 137,
            "ingredients": ["bacon", "cheese", "mayonnaise", "ketchup", "pickles", "burger bun", "beef"]
          },
          {
            "name": "Bacon Melt",
            "restaurant": "Burger King",
            "calories": 610,
            "type": "Burger",
            "vegan": false,
            "glutenFree": false,
            "yearOfRelease": "2000s",
            "game": 138,
            "ingredients": ["bacon", "cheese", "melted cheese", "onions", "burger bun", "beef"]
          },
          {
            "name": "BBQ Bacon Whopper Jr",
            "restaurant": "Burger King",
            "calories": 398,
            "type": "Burger",
            "vegan": false,
            "glutenFree": false,
            "yearOfRelease": "2010s",
            "game": 139,
            "ingredients": ["bacon", "cheese", "BBQ sauce", "pickles", "lettuce", "tomato", "burger bun", "beef"]
          },
          {
            "name": "Big King",
            "restaurant": "Burger King",
            "calories": 1009,
            "type": "Burger",
            "vegan": false,
            "glutenFree": false,
            "yearOfRelease": "2000s",
            "game": 140,
            "ingredients": ["cheese", "lettuce", "pickles", "onions", "burger bun", "beef"]
          },
          {
            "name": "Cheeseburger",
            "restaurant": "Burger King",
            "calories": 283,
            "type": "Burger",
            "vegan": false,
            "glutenFree": false,
            "yearOfRelease": "1970s",
            "game": 141,
            "ingredients": ["cheese", "ketchup", "mustard", "pickles", "burger bun", "beef"]
          },
          {
            "name": "Classic Melt",
            "restaurant": "Burger King",
            "calories": 575,
            "type": "Burger",
            "vegan": false,
            "glutenFree": false,
            "yearOfRelease": "2000s",
            "game": 142,
            "ingredients": ["cheese", "melted cheese", "onions", "burger bun", "beef"]
          },
          {
            "name": "Double BK Stacker",
            "restaurant": "Burger King",
            "calories": 1048,
            "type": "Burger",
            "vegan": false,
            "glutenFree": false,
            "yearOfRelease": "2000s",
            "game": 143,
            "ingredients": ["bacon", "cheese", "ketchup", "mayonnaise", "burger bun", "beef"]
          },
          {
            "name": "Double Cheeseburger",
            "restaurant": "Burger King",
            "calories": 388,
            "type": "Burger",
            "vegan": false,
            "glutenFree": false,
            "yearOfRelease": "1970s",
            "game": 144,
            "ingredients": ["cheese", "ketchup", "mustard", "pickles", "burger bun", "beef"]
          },
          {
            "name": "Double Quarter Pound King",
            "restaurant": "Burger King",
            "calories": 901,
            "type": "Burger",
            "vegan": false,
            "glutenFree": false,
            "yearOfRelease": "2010s",
            "game": 145,
            "ingredients": ["cheese", "pickles", "onions", "burger bun", "beef"]
          },
          {
            "name": "Double Whopper",
            "restaurant": "Burger King",
            "calories": "890-1002",
            "type": "Burger",
            "vegan": false,
            "glutenFree": false,
            "yearOfRelease": "1970s",
            "game": 146,
            "ingredients": ["cheese", "pickles", "lettuce", "onions", "burger bun", "beef"]
          },
          {
            "name": "French Onion Melt NEW",
            "restaurant": "Burger King",
            "calories": 600,
            "type": "Burger",
            "vegan": false,
            "glutenFree": false,
            "yearOfRelease": "2020s",
            "game": 147,
            "ingredients": ["cheese", "melted cheese", "onions", "burger bun", "beef"]
          },
          {
            "name": "Fried Pickle Ranch Whopper NEW",
            "restaurant": "Burger King",
            "calories": 870,
            "type": "Burger",
            "vegan": false,
            "glutenFree": false,
            "yearOfRelease": "2020s",
            "game": 148,
            "ingredients": ["fried pickles", "ranch sauce", "lettuce", "tomato", "onions", "burger bun", "beef"]
          },
          {
            "name": "Game Day Pretzel Whopper NEW",
            "restaurant": "Burger King",
            "calories": 870,
            "type": "Burger",
            "vegan": false,
            "glutenFree": false,
            "yearOfRelease": "2020s",
            "game": 149,
            "ingredients": ["pretzel bun", "cheese", "onions", "lettuce", "tomato", "beef"]
          },
          {
            "name": "Hamburger",
            "restaurant": "Burger King",
            "calories": 242,
            "type": "Burger",
            "vegan": false,
            "glutenFree": false,
            "yearOfRelease": "1970s",
            "game": 150,
            "ingredients": ["ketchup", "mustard", "pickles", "onions", "burger bun", "beef"]
          },
          {
            "name": "Impossible Whopper",
            "restaurant": "Burger King",
            "calories": 629,
            "type": "Burger",
            "vegan": true,
            "glutenFree": false,
            "yearOfRelease": "2019",
            "game": 151,
            "ingredients": ["impossible patty", "lettuce", "tomato", "pickles", "onions", "ketchup", "mayonnaise", "burger bun"]
          },
          {
            "name": "Maple Bourbon BBQ Whopper NEW",
            "restaurant": "Burger King",
            "calories": 880,
            "type": "Burger",
            "vegan": false,
            "glutenFree": false,
            "yearOfRelease": "2020s",
            "game": 152,
            "ingredients": ["maple bourbon BBQ sauce", "bacon", "cheese", "lettuce", "tomato", "onions", "burger bun", "beef"]
          },
          {
            "name": "Mexican Street Corn Whopper NEW",
            "restaurant": "Burger King",
            "calories": 710,
            "type": "Burger",
            "vegan": false,
            "glutenFree": false,
            "yearOfRelease": "2020s",
            "game": 153,
            "ingredients": ["street corn sauce", "corn", "cheese", "jalapeños", "lettuce", "tomato", "burger bun", "beef"]
          },
          {
            "name": "Miami BK Stacker",
            "restaurant": "Burger King",
            "calories": 571,
            "type": "Burger",
            "vegan": false,
            "glutenFree": false,
            "yearOfRelease": "2010s",
            "game": 154,
            "ingredients": ["bacon", "cheese", "stacker sauce", "burger bun", "beef"]
          },
          {
            "name": "Philly BK Stacker",
            "restaurant": "Burger King",
            "calories": 520,
            "type": "Burger",
            "vegan": false,
            "glutenFree": false,
            "yearOfRelease": "2010s",
            "game": 155,
            "ingredients": ["cheese", "grilled onions", "peppers", "stacker sauce", "burger bun", "beef"]
          },
          {
            "name": "Quad BK Stacker",
            "restaurant": "Burger King",
            "calories": 820,
            "type": "Burger",
            "vegan": false,
            "glutenFree": false,
            "yearOfRelease": "2010s",
            "game": 156,
            "ingredients": ["beef", "bacon", "cheese", "stacker sauce", "burger bun"]
          },
          {
            "name": "Quarter Pound King",
            "restaurant": "Burger King",
            "calories": 580,
            "type": "Burger",
            "vegan": false,
            "glutenFree": false,
            "yearOfRelease": "2010s",
            "game": 157,
            "ingredients": ["cheese", "pickles", "onions", "ketchup", "mustard", "burger bun", "beef"]
          },
          {
            "name": "Rodeo Burger",
            "restaurant": "Burger King",
            "calories": 340,
            "type": "Burger",
            "vegan": false,
            "glutenFree": false,
            "yearOfRelease": "2000s",
            "game": 158,
            "ingredients": ["onion rings", "BBQ sauce", "cheese", "burger bun", "beef"]
          },
          {
            "name": "Shroom n' Swiss Melt",
            "restaurant": "Burger King",
            "calories": 659,
            "type": "Burger",
            "vegan": false,
            "glutenFree": false,
            "yearOfRelease": "2010s",
            "game": 159,
            "ingredients": ["mushrooms", "swiss cheese", "melted cheese", "onions", "burger bun", "beef"]
          },
          {
            "name": "Single Impossible King",
            "restaurant": "Burger King",
            "calories": 552,
            "type": "Burger",
            "vegan": true,
            "glutenFree": false,
            "yearOfRelease": "2020s",
            "game": 160,
            "ingredients": ["impossible patty", "cheese", "pickles", "onions", "ketchup", "mustard", "burger bun"]
          },
          {
            "name": "Texas BK Stacker",
            "restaurant": "Burger King",
            "calories": 585,
            "type": "Burger",
            "vegan": false,
            "glutenFree": false,
            "yearOfRelease": "2010s",
            "game": 161,
            "ingredients": ["bacon", "cheese", "onion rings", "BBQ sauce", "burger bun", "beef"]
          },
          {
            "name": "Texas Double Whopper",
            "restaurant": "Burger King",
            "calories": 1056,
            "type": "Burger",
            "vegan": false,
            "glutenFree": false,
            "yearOfRelease": "2010s",
            "game": 162,
            "ingredients": ["bacon", "cheese", "lettuce", "tomato", "onions", "BBQ sauce", "burger bun", "beef"]
          },
          {
            "name": "Triple BK Stacker",
            "restaurant": "Burger King",
            "calories": 1370,
            "type": "Burger",
            "vegan": false,
            "glutenFree": false,
            "yearOfRelease": "2010s",
            "game": 163,
            "ingredients": ["beef", "bacon", "cheese", "stacker sauce", "burger bun"]
          },
          {
            "name": "Triple Whopper",
            "restaurant": "Burger King",
            "calories": "1140-1216",
            "type": "Burger",
            "vegan": false,
            "glutenFree": false,
            "yearOfRelease": "2000s",
            "game": 164,
            "ingredients": ["lettuce", "tomato", "pickles", "onions", "cheese", "burger bun", "beef"]
          },
          {
            "name": "Whopper",
            "restaurant": "Burger King",
            "calories": "657-740",
            "type": "Burger",
            "vegan": false,
            "glutenFree": false,
            "yearOfRelease": "1950s",
            "game": 165,
            "ingredients": ["lettuce", "tomato", "pickles", "onions", "ketchup", "mayonnaise", "bun", "beef"]
          },
          {
            "name": "Whopper Jr",
            "restaurant": "Burger King",
            "calories": "315-380",
            "type": "Burger",
            "vegan": false,
            "glutenFree": false,
            "yearOfRelease": "1960s",
            "game": 166,
            "ingredients": ["lettuce", "tomato", "pickles", "onions", "ketchup", "mayonnaise", "burger bun", "beef"]
          },
          {
            "name": "Crispy Taco",
            "restaurant": "Burger King",
            "calories": 170,
            "type": "Side",
            "vegan": false,
            "glutenFree": false,
            "yearOfRelease": "2010s",
            "game": 167,
            "ingredients": ["taco shell", "seasoned beef", "cheese", "lettuce"]
          },
          {
            "name": "French Fries",
            "restaurant": "Burger King",
            "calories": "223-434",
            "type": "Side",
            "vegan": true,
            "glutenFree": false,
            "yearOfRelease": "1970s",
            "game": 168,
            "ingredients": ["potatoes", "vegetable oil", "salt"]
          },
          {
            "name": "Motts' Applesauce",
            "restaurant": "Burger King",
            "calories": 50,
            "type": "Side",
            "vegan": true,
            "glutenFree": true,
            "yearOfRelease": "2010s",
            "game": 169,
            "ingredients": ["apples", "ascorbic acid"]
          },
          {
            "name": "Mozzarella Fries",
            "restaurant": "Burger King",
            "calories": "240-730",
            "type": "Side",
            "vegan": false,
            "glutenFree": false,
            "yearOfRelease": "2020s",
            "game": 170,
            "ingredients": ["mozzarella cheese", "breaded coating", "oil"]
          },
          {
            "name": "Onion Rings",
            "restaurant": "Burger King",
            "calories": "302-652",
            "type": "Side",
            "vegan": false,
            "glutenFree": false,
            "yearOfRelease": "1980s",
            "game": 171,
            "ingredients": ["onions", "breading", "vegetable oil"]
          },
          {
            "name": "Pickle Fries NEW",
            "restaurant": "Burger King",
            "calories": 380,
            "type": "Side",
            "vegan": false,
            "glutenFree": false,
            "yearOfRelease": "2020s",
            "game": 172,
            "ingredients": ["pickles", "breading", "oil"]
          },
          {
            "name": "Chocolate Chip Cookie",
            "restaurant": "Burger King",
            "calories": 330,
            "type": "Dessert",
            "vegan": false,
            "glutenFree": false,
            "yearOfRelease": "2000s",
            "game": 173,
            "ingredients": ["flour", "sugar", "chocolate chips", "eggs", "butter"]
          },
          {
            "name": "Chocolate Milk Shake",
            "restaurant": "Burger King",
            "calories": 762,
            "type": "Dessert",
            "vegan": false,
            "glutenFree": false,
            "yearOfRelease": "1970s",
            "game": 174,
            "ingredients": ["chocolate syrup", "milk", "soft serve"]
          },
          {
            "name": "Chocolate Oreo Shake",
            "restaurant": "Burger King",
            "calories": 717,
            "type": "Dessert",
            "vegan": false,
            "glutenFree": false,
            "yearOfRelease": "2010s",
            "game": 175,
            "ingredients": ["oreo cookies", "chocolate syrup", "milk", "soft serve"]
          },
          {
            "name": "Cookie Batter Shake",
            "restaurant": "Burger King",
            "calories": 969,
            "type": "Dessert",
            "vegan": false,
            "glutenFree": false,
            "yearOfRelease": "2020s",
            "game": 176,
            "ingredients": ["cookie dough", "milk", "soft serve"]
          },
          {
            "name": "Hershey Pie Shake",
            "restaurant": "Burger King",
            "calories": 857,
            "type": "Dessert",
            "vegan": false,
            "glutenFree": false,
            "yearOfRelease": "2020s",
            "game": 177,
            "ingredients": ["hershey pie pieces", "chocolate", "milk", "soft serve"]
          },
          {
            "name": "Hershey's Sundae Pie",
            "restaurant": "Burger King",
            "calories": 306,
            "type": "Dessert",
            "vegan": false,
            "glutenFree": false,
            "yearOfRelease": "2000s",
            "game": 178,
            "ingredients": ["chocolate", "whipped topping", "cookie crust"]
          },
          {
            "name": "Oreo Shake",
            "restaurant": "Burger King",
            "calories": 715,
            "type": "Dessert",
            "vegan": false,
            "glutenFree": false,
            "yearOfRelease": "2010s",
            "game": 179,
            "ingredients": ["oreo cookies", "milk", "soft serve"]
          },
          {
            "name": "Soft Serve Ice Cream Cone",
            "restaurant": "Burger King",
            "calories": 142,
            "type": "Dessert",
            "vegan": false,
            "glutenFree": false,
            "yearOfRelease": "1970s",
            "game": 180,
            "ingredients": ["soft serve", "cone"]
          },
          {
            "name": "Soft Serve Ice Cream Cup",
            "restaurant": "Burger King",
            "calories": 171,
            "type": "Dessert",
            "vegan": false,
            "glutenFree": true,
            "yearOfRelease": "1970s",
            "game": 181,
            "ingredients": ["soft serve"]
          },
          {
            "name": "Spider-Verse Sundae",
            "restaurant": "Burger King",
            "calories": 250,
            "type": "Dessert",
            "vegan": false,
            "glutenFree": false,
            "yearOfRelease": "2020s",
            "game": 182,
            "ingredients": ["vanilla soft serve", "chocolate"]
          },
          {
            "name": "Strawberry Milk Shake",
            "restaurant": "Burger King",
            "calories": 644,
            "type": "Dessert",
            "vegan": false,
            "glutenFree": false,
            "yearOfRelease": "1970s",
            "game": 183,
            "ingredients": ["strawberry syrup", "milk", "soft serve"]
          },
          {
            "name": "Vanilla Milk Shake",
            "restaurant": "Burger King",
            "calories": 583,
            "type": "Dessert",
            "vegan": false,
            "glutenFree": false,
            "yearOfRelease": "1970s",
            "game": 184,
            "ingredients": ["vanilla syrup", "milk", "soft serve"]
          }
    ]
  